Workbook

Sheet Cleaned_Population
A1: County | B1: State | C1: Pop_2025
A2: Autauga | B2: Alabama | C2: 61920
A3: Baldwin | B3: Alabama | C3: 267761
A4: Barbour | B4: Alabama | C4: 24607
A5: Bibb | B5: Alabama | C5: 22262
A6: Blount | B6: Alabama | C6: 60156
A7: Bullock | B7: Alabama | C7: 9780
A8: Butler | B8: Alabama | C8: 18100
A9: Calhoun | B9: Alabama | C9: 115834
A10: Chambers | B10: Alabama | C10: 34253
A11: Cherokee | B11: Alabama | C11: 26413
A12: Chilton | B12: Alabama | C12: 47708
A13: Choctaw | B13: Alabama | C13: 11904
... A3145: Weston | B3145: Wyoming | C3145: 6840
A3146: The Census Bureau has reviewed this data product to ensure appropriate access | B3146: use, and disclosure avoidance protection of the confidential source data used to produce this product (Data Management System (DMS) number: P-6000042 and P-7501659. Disclosure Review Board (DRB) approval number: CBDRB-FY25-0466).
A3147: The estimates are based on the 2020 Modified Age and Race Census (MARC) file and include changes from Count Question Resolution | B3147: the Post-Census Group Quarters Review, and geographic revisions. The estimates add births to, subtract deaths from, and add net migration to the April 1, 2020 estimates base. For population estimates methodology statements, see https://www.census.gov/programs-surveys/popest/technical-documentation/methodology.html. All geographic boundaries for the 2025 population estimates series are as of January 1, 2025.
A3148: Suggested Citation:
A3149: Annual Estimates of the Resident Population for Counties in the United States: April 1 | B3149: 2020 to July 1, 2025 (CO-EST2025-POP)
A3150: Source: US Census Bureau | B3150: Population Division
A3151: Release Date: March 2026

Sheet Raw_Hospitals
A1: Facility Name | B1: City | C1: State | D1: County | E1: Hospital Type | F1: Hospital Ownership | G1: Emergency Services | H1: Hospital overall rating
A2: SOUTHEAST HEALTH MEDICAL CENTER | B2: DOTHAN | C2: AL | D2: HOUSTON | E2: Acute Care Hospitals | F2: Government - Hospital District or Authority | G2: Yes | H2: 4
A3: MARSHALL MEDICAL CENTERS | B3: BOAZ | C3: AL | D3: MARSHALL | E3: Acute Care Hospitals | F3: Government - Hospital District or Authority | G3: Yes | H3: 3
A4: NORTH ALABAMA MEDICAL CENTER | B4: FLORENCE | C4: AL | D4: LAUDERDALE | E4: Acute Care Hospitals | F4: Proprietary | G4: Yes | H4: 2
A5: MIZELL MEMORIAL HOSPITAL | B5: OPP | C5: AL | D5: COVINGTON | E5: Acute Care Hospitals | F5: Voluntary non-profit - Private | G5: Yes | H5: 1
A6: ST. VINCENT'S EAST | B6: BIRMINGHAM | C6: AL | D6: JEFFERSON | E6: Acute Care Hospitals | F6: Voluntary non-profit - Private | G6: Yes | H6: 3
A7: DEKALB REGIONAL MEDICAL CENTER | B7: FORT PAYNE | C7: AL | D7: DE KALB | E7: Acute Care Hospitals | F7: Proprietary | G7: Yes | H7: 2
A8: SHELBY BAPTIST MEDICAL CENTER | B8: ALABASTER | C8: AL | D8: SHELBY | E8: Acute Care Hospitals | F8: Voluntary non-profit - Private | G8: Yes | H8: 2
A9: UAB CALLAHAN EYE HOSPITAL AUTHORITY | B9: BIRMINGHAM | C9: AL | D9: JEFFERSON | E9: Acute Care Hospitals | F9: Voluntary non-profit - Private | G9: Yes
A10: HELEN KELLER HOSPITAL | B10: SHEFFIELD | C10: AL | D10: COLBERT | E10: Acute Care Hospitals | F10: Government - Hospital District or Authority | G10: Yes | H10: 2
A11: DALE MEDICAL CENTER | B11: OZARK | C11: AL | D11: DALE | E11: Acute Care Hospitals | F11: Government - Hospital District or Authority | G11: Yes
A12: FLOYD CHEROKEE MEDICAL CENTER | B12: CENTRE | C12: AL | D12: CHEROKEE | E12: Acute Care Hospitals | F12: Proprietary | G12: Yes
A13: BAPTIST MEDICAL CENTER SOUTH | B13: MONTGOMERY | C13: AL | D13: MONTGOMERY | E13: Acute Care Hospitals | F13: Government - Hospital District or Authority | G13: Yes | H13: 2
A14: JACKSON HOSPITAL & CLINIC INC | B14: MONTGOMERY | C14: AL | D14: MONTGOMERY | E14: Acute Care Hospitals | F14: Voluntary non-profit - Private | G14: Yes | H14: 2
A15: THE EAST ALABAMA HEALTHCARE AUTHORITY | B15: OPELIKA | C15: AL | D15: LEE | E15: Acute Care Hospitals | F15: Government - Hospital District or Authority | G15: Yes | H15: 3
A16: UNIVERSITY OF ALABAMA HOSPITAL | B16: BIRMINGHAM | C16: AL | D16: JEFFERSON | E16: Acute Care Hospitals | F16: Government - State | G16: Yes | H16: 2
A17: COMMUNITY HOSPITAL INC | B17: TALLASSEE | C17: AL | D17: ELMORE | E17: Acute Care Hospitals | F17: Voluntary non-profit - Private | G17: Yes
A18: CULLMAN REGIONAL MEDICAL CENTER | B18: CULLMAN | C18: AL | D18: CULLMAN | E18: Acute Care Hospitals | F18: Government - Hospital District or Authority | G18: Yes | H18: 2
A19: ANDALUSIA HEALTH | B19: ANDALUSIA | C19: AL | D19: COVINGTON | E19: Acute Care Hospitals | F19: Proprietary | G19: Yes | H19: 2
A20: HUNTSVILLE HOSPITAL | B20: HUNTSVILLE | C20: AL | D20: MADISON | E20: Acute Care Hospitals | F20: Government - Hospital District or Authority | G20: Yes | H20: 3
A21: GADSDEN REGIONAL MEDICAL CENTER | B21: GADSDEN | C21: AL | D21: ETOWAH | E21: Acute Care Hospitals | F21: Proprietary | G21: Yes | H21: 2
A22: MARION REGIONAL MEDICAL CENTER | B22: HAMILTON | C22: AL | D22: MARION | E22: Acute Care Hospitals | F22: Voluntary non-profit - Private | G22: Yes | H22: 3
A23: FAYETTE MEDICAL CENTER | B23: FAYETTE | C23: AL | D23: FAYETTE | E23: Acute Care Hospitals | F23: Voluntary non-profit - Other | G23: Yes | H23: 4
A24: RIVERVIEW REGIONAL MEDICAL CENTER | B24: GADSDEN | C24: AL | D24: ETOWAH | E24: Acute Care Hospitals | F24: Proprietary | G24: Yes | H24: 3
A25: MEDICAL CENTER ENTERPRISE | B25: ENTERPRISE | C25: AL | D25: COFFEE | E25: Acute Care Hospitals | F25: Proprietary | G25: Yes | H25: 4
A26: GREENE COUNTY HOSPITAL | B26: EUTAW | C26: AL | D26: GREENE | E26: Acute Care Hospitals | F26: Voluntary non-profit - Other | G26: Yes
A27: LAKE MARTIN COMMUNITY HOSPITAL | B27: DADEVILLE | C27: AL | D27: TALLAPOOSA | E27: Acute Care Hospitals | F27: Proprietary | G27: Yes
A28: FLOWERS HOSPITAL | B28: DOTHAN | C28: AL | D28: HOUSTON | E28: Acute Care Hospitals | F28: Proprietary | G28: Yes | H28: 2
A29: ST VINCENT'S BIRMINGHAM | B29: BIRMINGHAM | C29: AL | D29: JEFFERSON | E29: Acute Care Hospitals | F29: Voluntary non-profit - Private | G29: Yes | H29: 3
A30: BIBB MEDICAL CENTER | B30: CENTREVILLE | C30: AL | D30: BIBB | E30: Acute Care Hospitals | F30: Government - Hospital District or Authority | G30: Yes
A31: HIGHLANDS MEDICAL CENTER | B31: SCOTTSBORO | C31: AL | D31: JACKSON | E31: Acute Care Hospitals | F31: Government - Hospital District or Authority | G31: Yes | H31: 3
A32: WIREGRASS MEDICAL CENTER | B32: GENEVA | C32: AL | D32: GENEVA | E32: Acute Care Hospitals | F32: Government - Hospital District or Authority | G32: Yes
A33: RUSSELL MEDICAL CENTER | B33: ALEXANDER CITY | C33: AL | D33: TALLAPOOSA | E33: Acute Care Hospitals | F33: Voluntary non-profit - Private | G33: Yes | H33: 3
A34: CLAY COUNTY HOSPITAL | B34: ASHLAND | C34: AL | D34: CLAY | E34: Acute Care Hospitals | F34: Government - Hospital District or Authority | G34: Yes
A35: NORTHEAST ALABAMA REGIONAL MEDICAL CENTER | B35: ANNISTON | C35: AL | D35: CALHOUN | E35: Acute Care Hospitals | F35: Government - Local | G35: Yes | H35: 1
A36: ATHENS LIMESTONE HOSPITAL | B36: ATHENS | C36: AL | D36: LIMESTONE | E36: Acute Care Hospitals | F36: Government - Hospital District or Authority | G36: Yes | H36: 2
A37: BALDWIN HEALTH | B37: FOLEY | C37: AL | D37: BALDWIN | E37: Acute Care Hospitals | F37: Proprietary | G37: Yes | H37: 4
A38: DECATUR MORGAN HOSPITAL - DECATUR CAMPUS | B38: DECATUR | C38: AL | D38: MORGAN | E38: Acute Care Hospitals | F38: Government - Hospital District or Authority | G38: Yes | H38: 3
A39: NORTHWEST MEDICAL CENTER | B39: WINFIELD | C39: AL | D39: FAYETTE | E39: Acute Care Hospitals | F39: Proprietary | G39: Yes | H39: 4
A40: USA HEALTH UNIVERSITY HOSPITAL | B40: MOBILE | C40: AL | D40: MOBILE | E40: Acute Care Hospitals | F40: Government - State | G40: Yes | H40: 2
A41: WALKER BAPTIST MEDICAL CENTER | B41: JASPER | C41: AL | D41: WALKER | E41: Acute Care Hospitals | F41: Proprietary | G41: Yes | H41: 3
A42: USA HEALTH HCA PROVIDENCE HOSPITAL, LLC | B42: MOBILE | C42: AL | D42: MOBILE | E42: Acute Care Hospitals | F42: Voluntary non-profit - Church | G42: Yes | H42: 3
A43: GROVE HILL MEMORIAL HOSPITAL | B43: GROVE HILL | C43: AL | D43: CLARKE | E43: Acute Care Hospitals | F43: Government - Hospital District or Authority | G43: Yes
A44: DCH REGIONAL MEDICAL CENTER | B44: TUSCALOOSA | C44: AL | D44: TUSCALOOSA | E44: Acute Care Hospitals | F44: Government - Hospital District or Authority | G44: Yes | H44: 2
A45: HALE COUNTY HOSPITAL | B45: GREENSBORO | C45: AL | D45: HALE | E45: Acute Care Hospitals | F45: Government - Hospital District or Authority | G45: Yes
A46: ELMORE COMMUNITY HOSPITAL | B46: WETUMPKA | C46: AL | D46: ELMORE | E46: Acute Care Hospitals | F46: Proprietary | G46: Yes
A47: D W MCMILLAN MEMORIAL HOSPITAL | B47: BREWTON | C47: AL | D47: ESCAMBIA | E47: Acute Care Hospitals | F47: Government - Hospital District or Authority | G47: Yes | H47: 1
A48: THOMAS HOSPITAL | B48: FAIRHOPE | C48: AL | D48: BALDWIN | E48: Acute Care Hospitals | F48: Voluntary non-profit - Private | G48: Yes | H48: 2
A49: CITIZENS BAPTIST MEDICAL CENTER | B49: TALLADEGA | C49: AL | D49: TALLADEGA | E49: Acute Care Hospitals | F49: Voluntary non-profit - Private | G49: Yes | H49: 1
A50: PRINCETON BAPTIST MEDICAL CENTER | B50: BIRMINGHAM | C50: AL | D50: JEFFERSON | E50: Acute Care Hospitals | F50: Voluntary non-profit - Church | G50: Yes | H50: 3
A51: GRANDVIEW MEDICAL CENTER | B51: BIRMINGHAM | C51: AL | D51: JEFFERSON | E51: Acute Care Hospitals | F51: Proprietary | G51: Yes | H51: 3
A52: PRATTVILLE BAPTIST HOSPITAL | B52: PRATTVILLE | C52: AL | D52: AUTAUGA | E52: Acute Care Hospitals | F52: Government - Hospital District or Authority | G52: Yes | H52: 3
A53: BULLOCK COUNTY HOSPITAL | B53: UNION SPRINGS | C53: AL | D53: BULLOCK | E53: Acute Care Hospitals | F53: Proprietary | G53: Yes
A54: WHITFIELD REGIONAL HOSPITAL | B54: DEMOPOLIS | C54: AL | D54: MARENGO | E54: Acute Care Hospitals | F54: Government - Hospital District or Authority | G54: Yes | H54: 2
A55: MOBILE INFIRMARY MEDICAL CENTER | B55: MOBILE | C55: AL | D55: MOBILE | E55: Acute Care Hospitals | F55: Voluntary non-profit - Private | G55: Yes | H55: 2
A56: MEDICAL WEST, AN AFFILIATE OF UAB HEALTH SYSTEM | B56: BESSEMER | C56: AL | D56: JEFFERSON | E56: Acute Care Hospitals | F56: Government - Hospital District or Authority | G56: Yes | H56: 3
A57: VAUGHAN REGIONAL MEDICAL CENTER PARKWAY CAMPUS | B57: SELMA | C57: AL | D57: DALLAS | E57: Acute Care Hospitals | F57: Proprietary | G57: Yes | H57: 2
A58: MONROE COUNTY HOSPITAL | B58: MONROEVILLE | C58: AL | D58: MONROE | E58: Acute Care Hospitals | F58: Government - Hospital District or Authority | G58: Yes | H58: 1
A59: LAKELAND COMMUNITY HOSPITAL | B59: HALEYVILLE | C59: AL | D59: WINSTON | E59: Acute Care Hospitals | F59: Proprietary | G59: Yes | H59: 3
A60: TROY REGIONAL MEDICAL CENTER | B60: TROY | C60: AL | D60: PIKE | E60: Acute Care Hospitals | F60: Government - Federal | G60: Yes | H60: 4
A61: JACKSON MEDICAL CENTER | B61: JACKSON | C61: AL | D61: CLARKE | E61: Acute Care Hospitals | F61: Proprietary | G61: Yes
A62: NORTH BALDWIN INFIRMARY | B62: BAY MINETTE | C62: AL | D62: BALDWIN | E62: Acute Care Hospitals | F62: Voluntary non-profit - Private | G62: Yes | H62: 3
A63: ST VINCENT'S ST CLAIR | B63: PELL CITY | C63: AL | D63: ST. CLAIR | E63: Acute Care Hospitals | F63: Voluntary non-profit - Private | G63: Yes | H63: 3
A64: CRESTWOOD MEDICAL CENTER | B64: HUNTSVILLE | C64: AL | D64: MADISON | E64: Acute Care Hospitals | F64: Proprietary | G64: Yes | H64: 3
A65: HILL HOSPITAL OF SUMTER COUNTY | B65: YORK | C65: AL | D65: SUMTER | E65: Acute Care Hospitals | F65: Government - Hospital District or Authority | G65: Yes
A66: BAPTIST HEALTH BROOKWOOD HOSPITAL | B66: VESTAVIA | C66: AL | D66: JEFFERSON | E66: Acute Care Hospitals | F66: Proprietary | G66: Yes | H66: 3
A67: SPRINGHILL MEDICAL CENTER | B67: MOBILE | C67: AL | D67: MOBILE | E67: Acute Care Hospitals | F67: Proprietary | G67: Yes | H67: 3
A68: EVERGREEN MEDICAL CENTER | B68: EVERGREEN | C68: AL | D68: CONECUH | E68: Acute Care Hospitals | F68: Proprietary | G68: Yes | H68: 3
A69: BAPTIST MEDICAL CENTER EAST | B69: MONTGOMERY | C69: AL | D69: MONTGOMERY | E69: Acute Care Hospitals | F69: Government - Hospital District or Authority | G69: Yes | H69: 4
A70: BIRMINGHAM VA MEDICAL CENTER | B70: BIRMINGHAM | C70: AL | D70: JEFFERSON | E70: Acute Care - Veterans Administration | F70: Veterans Health Administration | G70: Yes | H70: 4
A71: THE HEALTH CARE AUTHORITY OF THE CITY OF GREENVILLE- LV STABLER HOSPITAL | B71: GREENVILLE | C71: AL | D71: BUTLER | E71: Acute Care Hospitals | F71: Proprietary | G71: Yes
A72: NORTH ALABAMA SHOALS HOSPITAL | B72: MUSCLE SHOALS | C72: AL | D72: COLBERT | E72: Acute Care Hospitals | F72: Proprietary | G72: Yes
A73: RUSSELLVILLE HOSPITAL | B73: RUSSELLVILLE | C73: AL | D73: FRANKLIN | E73: Acute Care Hospitals | F73: Proprietary | G73: Yes | H73: 4
A74: COOSA VALLEY MEDICAL CENTER | B74: SYLACAUGA | C74: AL | D74: TALLADEGA | E74: Acute Care Hospitals | F74: Government - Hospital District or Authority | G74: Yes | H74: 3
A75: JACK HUGHSTON MEMORIAL HOSPITAL | B75: PHENIX CITY | C75: AL | D75: RUSSELL | E75: Acute Care Hospitals | F75: Government - State | G75: Yes | H75: 4
A76: ATMORE COMMUNITY HOSPITAL | B76: ATMORE | C76: AL | D76: ESCAMBIA | E76: Acute Care Hospitals | F76: Government - Hospital District or Authority | G76: Yes | H76: 3
A77: ST VINCENT'S CHILTON | B77: CLANTON | C77: AL | D77: CHILTON | E77: Acute Care Hospitals | F77: Voluntary non-profit - Church | G77: Yes
A78: VA CENTRAL ALABAMA HEALTHCARE SYSTEM - MONTGOMERY | B78: MONTGOMERY | C78: AL | D78: MONTGOMERY | E78: Acute Care - Veterans Administration | F78: Veterans Health Administration | G78: Yes | H78: 4
A79: TUSCALOOSA VA MEDICAL CENTER | B79: TUSCALOOSA | C79: AL | D79: TUSCALOOSA | E79: Acute Care - Veterans Administration | F79: Veterans Health Administration | G79: No
A80: BULLOCK COUNTY HOSPITAL | B80: UNION SPRINGS | C80: AL | D80: BULLOCK | E80: Rural Emergency Hospital | F80: Proprietary | G80: Yes
A81: EAMC - LANIER | B81: VALLEY | C81: AL | D81: CHAMBERS | E81: Rural Emergency Hospital | F81: Government - Hospital District or Authority | G81: Yes
A82: J PAUL JONES HOSPITAL | B82: CAMDEN | C82: AL | D82: WILCOX | E82: Rural Emergency Hospital | F82: Government - Local | G82: Yes
A83: WASHINGTON COUNTY HOSPITAL | B83: CHATOM | C83: AL | D83: WASHINGTON | E83: Critical Access Hospitals | F83: Government - Local | G83: Yes
A84: RED BAY HOSPITAL | B84: RED BAY | C84: AL | D84: FRANKLIN | E84: Critical Access Hospitals | F84: Government - Hospital District or Authority | G84: Yes
A85: OCHSNER CHOCTAW GENERAL | B85: BUTLER | C85: AL | D85: CHOCTAW | E85: Critical Access Hospitals | F85: Voluntary non-profit - Private | G85: Yes
A86: ST VINCENTS BLOUNT | B86: ONEONTA | C86: AL | D86: BLOUNT | E86: Critical Access Hospitals | F86: Voluntary non-profit - Private | G86: No
A87: TANNER MEDICAL CENTER-EAST ALABAMA | B87: WEDOWEE | C87: AL | D87: RANDOLPH | E87: Critical Access Hospitals | F87: Government - Hospital District or Authority | G87: Yes
A88: MEDICAL CENTER BARBOUR | B88: EUFAULA | C88: AL | D88: BARBOUR | E88: Critical Access Hospitals | F88: Government - Hospital District or Authority | G88: Yes
A89: CRENSHAW COMMUNITY HOSPITAL | B89: LUVERNE | C89: AL | D89: CRENSHAW | E89: Critical Access Hospitals | F89: Government - Hospital District or Authority | G89: Yes
A90: WIREGRASS MEDICAL CENTER | B90: GENEVA | C90: AL | D90: GENEVA | E90: Critical Access Hospitals | F90: Government - Hospital District or Authority | G90: Yes
... A101: UNITY PSYCHIATRIC CARE - HUNTSVILLE | B101: HUNTSVILLE | C101: AL | D101: MADISON | E101: Psychiatric | F101: Proprietary | G101: No
A102: PROVIDENCE ALASKA MEDICAL CENTER | B102: ANCHORAGE | C102: AK | D102: ANCHORAGE | E102: Acute Care Hospitals | F102: Voluntary non-profit - Church | G102: Yes | H102: 3
A103: MAT-SU REGIONAL MEDICAL CENTER | B103: PALMER | C103: AK | D103: MATANUSKA-SUSITNA | E103: Acute Care Hospitals | F103: Voluntary non-profit - Other | G103: Yes | H103: 3
A104: BARTLETT REGIONAL HOSPITAL | B104: JUNEAU | C104: AK | D104: JUNEAU | E104: Acute Care Hospitals | F104: Government - Local | G104: Yes | H104: 4
A105: FAIRBANKS MEMORIAL HOSPITAL | B105: FAIRBANKS | C105: AK | D105: FAIRBANKS NORTH STAR | E105: Acute Care Hospitals | F105: Voluntary non-profit - Private | G105: Yes | H105: 2
A106: ALASKA REGIONAL HOSPITAL | B106: ANCHORAGE | C106: AK | D106: ANCHORAGE | E106: Acute Care Hospitals | F106: Proprietary | G106: Yes | H106: 1
A107: YUKON KUSKOKWIM DELTA REG HOSPITAL | B107: BETHEL | C107: AK | D107: BETHEL | E107: Acute Care Hospitals | F107: Tribal | G107: Yes | H107: 5
A108: CENTRAL PENINSULA GENERAL HOSPITAL | B108: SOLDOTNA | C108: AK | D108: KENAI PENINSULA | E108: Acute Care Hospitals | F108: Voluntary non-profit - Other | G108: Yes | H108: 2
A109: ALASKA NATIVE MEDICAL CENTER | B109: ANCHORAGE | C109: AK | D109: ANCHORAGE | E109: Acute Care Hospitals | F109: Government - Federal | G109: Yes | H109: 2
A110: 673rd Medical Group (Joint Base Elmendorf-Richardson) | B110: JBER | C110: AK | D110: ANCHORAGE | E110: Acute Care - Department of Defense | F110: Department of Defense | G110: Yes
...

Sheet State_Ref
A1: State_Full | B1: State_Abbr
A2: Alabama | B2: AL
A3: Alaska | B3: AK
A4: Arizona | B4: AZ
A5: Arkansas | B5: AR
A6: California | B6: CA
A7: Colorado | B7: CO
A8: Connecticut | B8: CT
A9: Delaware | B9: DE
A10: Florida | B10: FL
A11: Georgia | B11: GA
A12: Hawaii | B12: HI
... A51: Wyoming | B51: WY

Sheet Merged_Data
A1: Facility Name | B1: City | C1: State | D1: County | E1: Hospital Type | F1: Hospital Ownership | G1: Emergency Services | H1: Hospital overall rating | I1: State_Full | J1: Pop_2025 | K1: Desert_Flag
A2: {=Hospital_General_Information[Facility Name]} -> SOUTHEAST HEALTH MEDICAL CENTER | B2: {=Hospital_General_Information[City]} -> DOTHAN | C2: {=Hospital_General_Information[State]} -> AL | D2: {=Hospital_General_Information[County]} -> HOUSTON | E2: {=Hospital_General_Information[Hospital Type]} -> Acute Care Hospitals | F2: {=Hospital_General_Information[Hospital Ownership]} -> Government - Hospital District or Authority | G2: {=Hospital_General_Information[Emergency Services]} -> Yes | H2: {=Hospital_General_Information[Hospital overall rating]} -> 4 | I2: =_xlfn.XLOOKUP(C2,State_Ref!B:B,State_Ref!A:A,"No Match") -> Alabama | J2: {=_xlfn.XLOOKUP(I2&PROPER(D2),Cleaned_Population!B$2:B$3200&Cleaned_Population!A$2:A$3200,Cleaned_Population!C$2:C$3200,"No Match")} -> 110318 | K2: =IF(AND(J2>50000,COUNTIFS(D:D,D2,C:C,C2)<=1),"Hospital Desert","Sufficient Access") -> Sufficient Access
A3: MARSHALL MEDICAL CENTERS | B3: BOAZ | C3: AL | D3: MARSHALL | E3: Acute Care Hospitals | F3: Government - Hospital District or Authority | G3: Yes | H3: 3 | I3: =_xlfn.XLOOKUP(C3,State_Ref!B:B,State_Ref!A:A,"No Match") -> Alabama | J3: {=_xlfn.XLOOKUP(I3&PROPER(D3),Cleaned_Population!B$2:B$3200&Cleaned_Population!A$2:A$3200,Cleaned_Population!C$2:C$3200,"No Match")} -> 103537 | K3: =IF(AND(J3>50000,COUNTIFS(D:D,D3,C:C,C3)<=1),"Hospital Desert","Sufficient Access") -> Hospital Desert
A4: NORTH ALABAMA MEDICAL CENTER | B4: FLORENCE | C4: AL | D4: LAUDERDALE | E4: Acute Care Hospitals | F4: Proprietary | G4: Yes | H4: 2 | I4: =_xlfn.XLOOKUP(C4,State_Ref!B:B,State_Ref!A:A,"No Match") -> Alabama | J4: {=_xlfn.XLOOKUP(I4&PROPER(D4),Cleaned_Population!B$2:B$3200&Cleaned_Population!A$2:A$3200,Cleaned_Population!C$2:C$3200,"No Match")} -> 97135 | K4: =IF(AND(J4>50000,COUNTIFS(D:D,D4,C:C,C4)<=1),"Hospital Desert","Sufficient Access") -> Hospital Desert
A5: MIZELL MEMORIAL HOSPITAL | B5: OPP | C5: AL | D5: COVINGTON | E5: Acute Care Hospitals | F5: Voluntary non-profit - Private | G5: Yes | H5: 1 | I5: =_xlfn.XLOOKUP(C5,State_Ref!B:B,State_Ref!A:A,"No Match") -> Alabama | J5: {=_xlfn.XLOOKUP(I5&PROPER(D5),Cleaned_Population!B$2:B$3200&Cleaned_Population!A$2:A$3200,Cleaned_Population!C$2:C$3200,"No Match")} -> 37947 | K5: =IF(AND(J5>50000,COUNTIFS(D:D,D5,C:C,C5)<=1),"Hospital Desert","Sufficient Access") -> Sufficient Access
A6: ST. VINCENT'S EAST | B6: BIRMINGHAM | C6: AL | D6: JEFFERSON | E6: Acute Care Hospitals | F6: Voluntary non-profit - Private | G6: Yes | H6: 3 | I6: =_xlfn.XLOOKUP(C6,State_Ref!B:B,State_Ref!A:A,"No Match") -> Alabama | J6: {=_xlfn.XLOOKUP(I6&PROPER(D6),Cleaned_Population!B$2:B$3200&Cleaned_Population!A$2:A$3200,Cleaned_Population!C$2:C$3200,"No Match")} -> 665742 | K6: =IF(AND(J6>50000,COUNTIFS(D:D,D6,C:C,C6)<=1),"Hospital Desert","Sufficient Access") -> Sufficient Access
A7: DEKALB REGIONAL MEDICAL CENTER | B7: FORT PAYNE | C7: AL | D7: DE KALB | E7: Acute Care Hospitals | F7: Proprietary | G7: Yes | H7: 2 | I7: =_xlfn.XLOOKUP(C7,State_Ref!B:B,State_Ref!A:A,"No Match") -> Alabama | J7: {=_xlfn.XLOOKUP(I7&PROPER(D7),Cleaned_Population!B$2:B$3200&Cleaned_Population!A$2:A$3200,Cleaned_Population!C$2:C$3200,"No Match")} -> No Match | K7: =IF(AND(J7>50000,COUNTIFS(D:D,D7,C:C,C7)<=1),"Hospital Desert","Sufficient Access") -> Hospital Desert
A8: SHELBY BAPTIST MEDICAL CENTER | B8: ALABASTER | C8: AL | D8: SHELBY | E8: Acute Care Hospitals | F8: Voluntary non-profit - Private | G8: Yes | H8: 2 | I8: =_xlfn.XLOOKUP(C8,State_Ref!B:B,State_Ref!A:A,"No Match") -> Alabama | J8: {=_xlfn.XLOOKUP(I8&PROPER(D8),Cleaned_Population!B$2:B$3200&Cleaned_Population!A$2:A$3200,Cleaned_Population!C$2:C$3200,"No Match")} -> 238552 | K8: =IF(AND(J8>50000,COUNTIFS(D:D,D8,C:C,C8)<=1),"Hospital Desert","Sufficient Access") -> Hospital Desert
A9: UAB CALLAHAN EYE HOSPITAL AUTHORITY | B9: BIRMINGHAM | C9: AL | D9: JEFFERSON | E9: Acute Care Hospitals | F9: Voluntary non-profit - Private | G9: Yes | H9: 0 | I9: =_xlfn.XLOOKUP(C9,State_Ref!B:B,State_Ref!A:A,"No Match") -> Alabama | J9: {=_xlfn.XLOOKUP(I9&PROPER(D9),Cleaned_Population!B$2:B$3200&Cleaned_Population!A$2:A$3200,Cleaned_Population!C$2:C$3200,"No Match")} -> 665742 | K9: =IF(AND(J9>50000,COUNTIFS(D:D,D9,C:C,C9)<=1),"Hospital Desert","Sufficient Access") -> Sufficient Access
A10: HELEN KELLER HOSPITAL | B10: SHEFFIELD | C10: AL | D10: COLBERT | E10: Acute Care Hospitals | F10: Government - Hospital District or Authority | G10: Yes | H10: 2 | I10: =_xlfn.XLOOKUP(C10,State_Ref!B:B,State_Ref!A:A,"No Match") -> Alabama | J10: {=_xlfn.XLOOKUP(I10&PROPER(D10),Cleaned_Population!B$2:B$3200&Cleaned_Population!A$2:A$3200,Cleaned_Population!C$2:C$3200,"No Match")} -> 59474 | K10: =IF(AND(J10>50000,COUNTIFS(D:D,D10,C:C,C10)<=1),"Hospital Desert","Sufficient Access") -> Sufficient Access
A11: DALE MEDICAL CENTER | B11: OZARK | C11: AL | D11: DALE | E11: Acute Care Hospitals | F11: Government - Hospital District or Authority | G11: Yes | H11: 0 | I11: =_xlfn.XLOOKUP(C11,State_Ref!B:B,State_Ref!A:A,"No Match") -> Alabama | J11: {=_xlfn.XLOOKUP(I11&PROPER(D11),Cleaned_Population!B$2:B$3200&Cleaned_Population!A$2:A$3200,Cleaned_Population!C$2:C$3200,"No Match")} -> 49912 | K11: =IF(AND(J11>50000,COUNTIFS(D:D,D11,C:C,C11)<=1),"Hospital Desert","Sufficient Access") -> Sufficient Access
A12: FLOYD CHEROKEE MEDICAL CENTER | B12: CENTRE | C12: AL | D12: CHEROKEE | E12: Acute Care Hospitals | F12: Proprietary | G12: Yes | H12: 0 | I12: =_xlfn.XLOOKUP(C12,State_Ref!B:B,State_Ref!A:A,"No Match") -> Alabama | J12: {=_xlfn.XLOOKUP(I12&PROPER(D12),Cleaned_Population!B$2:B$3200&Cleaned_Population!A$2:A$3200,Cleaned_Population!C$2:C$3200,"No Match")} -> 26413 | K12: =IF(AND(J12>50000,COUNTIFS(D:D,D12,C:C,C12)<=1),"Hospital Desert","Sufficient Access") -> Sufficient Access
A13: BAPTIST MEDICAL CENTER SOUTH | B13: MONTGOMERY | C13: AL | D13: MONTGOMERY | E13: Acute Care Hospitals | F13: Government - Hospital District or Authority | G13: Yes | H13: 2 | I13: =_xlfn.XLOOKUP(C13,State_Ref!B:B,State_Ref!A:A,"No Match") -> Alabama | J13: {=_xlfn.XLOOKUP(I13&PROPER(D13),Cleaned_Population!B$2:B$3200&Cleaned_Population!A$2:A$3200,Cleaned_Population!C$2:C$3200,"No Match")} -> 225891 | K13: =IF(AND(J13>50000,COUNTIFS(D:D,D13,C:C,C13)<=1),"Hospital Desert","Sufficient Access") -> Sufficient Access
A14: JACKSON HOSPITAL & CLINIC INC | B14: MONTGOMERY | C14: AL | D14: MONTGOMERY | E14: Acute Care Hospitals | F14: Voluntary non-profit - Private | G14: Yes | H14: 2 | I14: =_xlfn.XLOOKUP(C14,State_Ref!B:B,State_Ref!A:A,"No Match") -> Alabama | J14: {=_xlfn.XLOOKUP(I14&PROPER(D14),Cleaned_Population!B$2:B$3200&Cleaned_Population!A$2:A$3200,Cleaned_Population!C$2:C$3200,"No Match")} -> 225891 | K14: =IF(AND(J14>50000,COUNTIFS(D:D,D14,C:C,C14)<=1),"Hospital Desert","Sufficient Access") -> Sufficient Access
... A5433: EASTLAND MEMORIAL HOSPITAL | B5433: EASTLAND | C5433: TX | D5433: EASTLAND | E5433: Critical Access Hospitals | F5433: Government - Hospital District or Authority | G5433: Yes | H5433: 0 | I5433: =_xlfn.XLOOKUP(C5433,State_Ref!B:B,State_Ref!A:A,"No Match") -> Texas | J5433: {=_xlfn.XLOOKUP(I5433&PROPER(D5433),Cleaned_Population!B$2:B$3200&Cleaned_Population!A$2:A$3200,Cleaned_Population!C$2:C$3200,"No Match")} -> 18143 | K5433: =IF(AND(J5433>50000,COUNTIFS(D:D,D5433,C:C,C5433)<=1),"Hospital Desert","Sufficient Access") -> Sufficient Access

Sheet Analysis
A1: State | B1: Total_Hospitals | C1: Avg_Rating | D1: Emergency_Count | E1: Hospital_Deserts | F1: Avg_Population | G1: Rank
A2: =State_Ref!B45 -> UT | B2: =COUNTIFS(Merged_Data!C:C,A2) -> 52 | C2: =IFERROR(AVERAGEIFS(Merged_Data!H:H,Merged_Data!C:C,A2,Merged_Data!H:H,"<>0"),"No Data") -> 4.2413793 | D2: =COUNTIFS(Merged_Data!C:C,A2,Merged_Data!G:G,"Yes") -> 48 | E2: =COUNTIFS(Merged_Data!C:C,A2,Merged_Data!K:K,"Hospital Desert") -> 3 | F2: =IFERROR(AVERAGEIFS(Merged_Data!J:J,Merged_Data!C:C,A2,Merged_Data!J:J,"<>0"),"No Data") -> 484176.15 | G2: =RANK(B2,B$2:B$51,0) -> 37
A3: =State_Ref!B7 -> CO | B3: =COUNTIFS(Merged_Data!C:C,A3) -> 97 | C3: =IFERROR(AVERAGEIFS(Merged_Data!H:H,Merged_Data!C:C,A3,Merged_Data!H:H,"<>0"),"No Data") -> 3.9591837 | D3: =COUNTIFS(Merged_Data!C:C,A3,Merged_Data!G:G,"Yes") -> 88 | E3: =COUNTIFS(Merged_Data!C:C,A3,Merged_Data!K:K,"Hospital Desert") -> 3 | F3: =IFERROR(AVERAGEIFS(Merged_Data!J:J,Merged_Data!C:C,A3,Merged_Data!J:J,"<>0"),"No Data") -> 295686.91 | G3: =RANK(B3,B$2:B$51,0) -> 25
A4: =State_Ref!B42 -> SD | B4: =COUNTIFS(Merged_Data!C:C,A4) -> 61 | C4: =IFERROR(AVERAGEIFS(Merged_Data!H:H,Merged_Data!C:C,A4,Merged_Data!H:H,"<>0"),"No Data") -> 3.8888889 | D4: =COUNTIFS(Merged_Data!C:C,A4,Merged_Data!G:G,"Yes") -> 54 | E4: =COUNTIFS(Merged_Data!C:C,A4,Merged_Data!K:K,"Hospital Desert") -> 2 | F4: =IFERROR(AVERAGEIFS(Merged_Data!J:J,Merged_Data!C:C,A4,Merged_Data!J:J,"<>0"),"No Data") -> 40265.22 | G4: =RANK(B4,B$2:B$51,0) -> 34
A5: =State_Ref!B50 -> WI | B5: =COUNTIFS(Merged_Data!C:C,A5) -> 141 | C5: =IFERROR(AVERAGEIFS(Merged_Data!H:H,Merged_Data!C:C,A5,Merged_Data!H:H,"<>0"),"No Data") -> 3.7790698 | D5: =COUNTIFS(Merged_Data!C:C,A5,Merged_Data!G:G,"Yes") -> 126 | E5: =COUNTIFS(Merged_Data!C:C,A5,Merged_Data!K:K,"Hospital Desert") -> 3 | F5: =IFERROR(AVERAGEIFS(Merged_Data!J:J,Merged_Data!C:C,A5,Merged_Data!J:J,"<>0"),"No Data") -> 209352.18 | G5: =RANK(B5,B$2:B$51,0) -> 12
A6: =State_Ref!B24 -> MN | B6: =COUNTIFS(Merged_Data!C:C,A6) -> 136 | C6: =IFERROR(AVERAGEIFS(Merged_Data!H:H,Merged_Data!C:C,A6,Merged_Data!H:H,"<>0"),"No Data") -> 3.7719298 | D6: =COUNTIFS(Merged_Data!C:C,A6,Merged_Data!G:G,"Yes") -> 117 | E6: =COUNTIFS(Merged_Data!C:C,A6,Merged_Data!K:K,"Hospital Desert") -> 6 | F6: =IFERROR(AVERAGEIFS(Merged_Data!J:J,Merged_Data!C:C,A6,Merged_Data!J:J,"<>0"),"No Data") -> 164239.73 | G6: =RANK(B6,B$2:B$51,0) -> 14
A7: =State_Ref!B47 -> VA | B7: =COUNTIFS(Merged_Data!C:C,A7) -> 96 | C7: =IFERROR(AVERAGEIFS(Merged_Data!H:H,Merged_Data!C:C,A7,Merged_Data!H:H,"<>0"),"No Data") -> 3.6842105 | D7: =COUNTIFS(Merged_Data!C:C,A7,Merged_Data!G:G,"Yes") -> 84 | E7: =COUNTIFS(Merged_Data!C:C,A7,Merged_Data!K:K,"Hospital Desert") -> 19 | F7: =IFERROR(AVERAGEIFS(Merged_Data!J:J,Merged_Data!C:C,A7,Merged_Data!J:J,"<>0"),"No Data") -> 194131.54 | G7: =RANK(B7,B$2:B$51,0) -> 26
A8: =State_Ref!B36 -> OH | B8: =COUNTIFS(Merged_Data!C:C,A8) -> 196 | C8: =IFERROR(AVERAGEIFS(Merged_Data!H:H,Merged_Data!C:C,A8,Merged_Data!H:H,"<>0"),"No Data") -> 3.578125 | D8: =COUNTIFS(Merged_Data!C:C,A8,Merged_Data!G:G,"Yes") -> 139 | E8: =COUNTIFS(Merged_Data!C:C,A8,Merged_Data!K:K,"Hospital Desert") -> 17 | F8: =IFERROR(AVERAGEIFS(Merged_Data!J:J,Merged_Data!C:C,A8,Merged_Data!J:J,"<>0"),"No Data") -> 429056 | G8: =RANK(B8,B$2:B$51,0) -> 4
A9: =State_Ref!B13 -> ID | B9: =COUNTIFS(Merged_Data!C:C,A9) -> 48 | C9: =IFERROR(AVERAGEIFS(Merged_Data!H:H,Merged_Data!C:C,A9,Merged_Data!H:H,"<>0"),"No Data") -> 3.5454545 | D9: =COUNTIFS(Merged_Data!C:C,A9,Merged_Data!G:G,"Yes") -> 40 | E9: =COUNTIFS(Merged_Data!C:C,A9,Merged_Data!K:K,"Hospital Desert") -> 4 | F9: =IFERROR(AVERAGEIFS(Merged_Data!J:J,Merged_Data!C:C,A9,Merged_Data!J:J,"<>0"),"No Data") -> 131951.08 | G9: =RANK(B9,B$2:B$51,0) -> 38
A10: =State_Ref!B40 -> RI | B10: =COUNTIFS(Merged_Data!C:C,A10) -> 13 | C10: =IFERROR(AVERAGEIFS(Merged_Data!H:H,Merged_Data!C:C,A10,Merged_Data!H:H,"<>0"),"No Data") -> 3.5454545 | D10: =COUNTIFS(Merged_Data!C:C,A10,Merged_Data!G:G,"Yes") -> 12 | E10: =COUNTIFS(Merged_Data!C:C,A10,Merged_Data!K:K,"Hospital Desert") -> 2 | F10: =IFERROR(AVERAGEIFS(Merged_Data!J:J,Merged_Data!C:C,A10,Merged_Data!J:J,"<>0"),"No Data") -> 509211.31 | G10: =RANK(B10,B$2:B$51,0) -> 49
A11: =State_Ref!B28 -> NE | B11: =COUNTIFS(Merged_Data!C:C,A11) -> 93 | C11: =IFERROR(AVERAGEIFS(Merged_Data!H:H,Merged_Data!C:C,A11,Merged_Data!H:H,"<>0"),"No Data") -> 3.5 | D11: =COUNTIFS(Merged_Data!C:C,A11,Merged_Data!G:G,"Yes") -> 84 | E11: =COUNTIFS(Merged_Data!C:C,A11,Merged_Data!K:K,"Hospital Desert") -> 1 | F11: =IFERROR(AVERAGEIFS(Merged_Data!J:J,Merged_Data!C:C,A11,Merged_Data!J:J,"<>0"),"No Data") -> 112799.27 | G11: =RANK(B11,B$2:B$51,0) -> 27
A12: =State_Ref!B39 -> PA | B12: =COUNTIFS(Merged_Data!C:C,A12) -> 187 | C12: =IFERROR(AVERAGEIFS(Merged_Data!H:H,Merged_Data!C:C,A12,Merged_Data!H:H,"<>0"),"No Data") -> 3.4848485 | D12: =COUNTIFS(Merged_Data!C:C,A12,Merged_Data!G:G,"Yes") -> 148 | E12: =COUNTIFS(Merged_Data!C:C,A12,Merged_Data!K:K,"Hospital Desert") -> 10 | F12: =IFERROR(AVERAGEIFS(Merged_Data!J:J,Merged_Data!C:C,A12,Merged_Data!J:J,"<>0"),"No Data") -> 542388.13 | G12: =RANK(B12,B$2:B$51,0) -> 7
A13: =State_Ref!B41 -> SC | B13: =COUNTIFS(Merged_Data!C:C,A13) -> 66 | C13: =IFERROR(AVERAGEIFS(Merged_Data!H:H,Merged_Data!C:C,A13,Merged_Data!H:H,"<>0"),"No Data") -> 3.4285714 | D13: =COUNTIFS(Merged_Data!C:C,A13,Merged_Data!G:G,"Yes") -> 55 | E13: =COUNTIFS(Merged_Data!C:C,A13,Merged_Data!K:K,"Hospital Desert") -> 10 | F13: =IFERROR(AVERAGEIFS(Merged_Data!J:J,Merged_Data!C:C,A13,Merged_Data!J:J,"<>0"),"No Data") -> 268300.74 | G13: =RANK(B13,B$2:B$51,0) -> 31
A14: =State_Ref!B8 -> CT | B14: =COUNTIFS(Merged_Data!C:C,A14) -> 36 | C14: =IFERROR(AVERAGEIFS(Merged_Data!H:H,Merged_Data!C:C,A14,Merged_Data!H:H,"<>0"),"No Data") -> 3.4230769 | D14: =COUNTIFS(Merged_Data!C:C,A14,Merged_Data!G:G,"Yes") -> 27 | E14: =COUNTIFS(Merged_Data!C:C,A14,Merged_Data!K:K,"Hospital Desert") -> 0 | F14: =IFERROR(AVERAGEIFS(Merged_Data!J:J,Merged_Data!C:C,A14,Merged_Data!J:J,"<>0"),"No Data") -> No Data | G14: =RANK(B14,B$2:B$51,0) -> 42
A15: =State_Ref!B44 -> TX | B15: =COUNTIFS(Merged_Data!C:C,A15) -> 468 | C15: =IFERROR(AVERAGEIFS(Merged_Data!H:H,Merged_Data!C:C,A15,Merged_Data!H:H,"<>0"),"No Data") -> 3.3778802 | D15: =COUNTIFS(Merged_Data!C:C,A15,Merged_Data!G:G,"Yes") -> 389 | E15: =COUNTIFS(Merged_Data!C:C,A15,Merged_Data!K:K,"Hospital Desert") -> 24 | F15: =IFERROR(AVERAGEIFS(Merged_Data!J:J,Merged_Data!C:C,A15,Merged_Data!J:J,"<>0"),"No Data") -> 1220044.8 | G15: =RANK(B15,B$2:B$51,0) -> 1
A16: =State_Ref!B51 -> WY | B16: =COUNTIFS(Merged_Data!C:C,A16) -> 30 | C16: =IFERROR(AVERAGEIFS(Merged_Data!H:H,Merged_Data!C:C,A16,Merged_Data!H:H,"<>0"),"No Data") -> 3.375 | D16: =COUNTIFS(Merged_Data!C:C,A16,Merged_Data!G:G,"Yes") -> 25 | E16: =COUNTIFS(Merged_Data!C:C,A16,Merged_Data!K:K,"Hospital Desert") -> 0 | F16: =IFERROR(AVERAGEIFS(Merged_Data!J:J,Merged_Data!C:C,A16,Merged_Data!J:J,"<>0"),"No Data") -> 31848.1 | G16: =RANK(B16,B$2:B$51,0) -> 44
A17: =State_Ref!B15 -> IN | B17: =COUNTIFS(Merged_Data!C:C,A17) -> 151 | C17: =IFERROR(AVERAGEIFS(Merged_Data!H:H,Merged_Data!C:C,A17,Merged_Data!H:H,"<>0"),"No Data") -> 3.3626374 | D17: =COUNTIFS(Merged_Data!C:C,A17,Merged_Data!G:G,"Yes") -> 117 | E17: =COUNTIFS(Merged_Data!C:C,A17,Merged_Data!K:K,"Hospital Desert") -> 5 | F17: =IFERROR(AVERAGEIFS(Merged_Data!J:J,Merged_Data!C:C,A17,Merged_Data!J:J,"<>0"),"No Data") -> 239447.9 | G17: =RANK(B17,B$2:B$51,0) -> 9
A18: =State_Ref!B21 -> MD | B18: =COUNTIFS(Merged_Data!C:C,A18) -> 56 | C18: =IFERROR(AVERAGEIFS(Merged_Data!H:H,Merged_Data!C:C,A18,Merged_Data!H:H,"<>0"),"No Data") -> 3.3095238 | D18: =COUNTIFS(Merged_Data!C:C,A18,Merged_Data!G:G,"Yes") -> 43 | E18: =COUNTIFS(Merged_Data!C:C,A18,Merged_Data!K:K,"Hospital Desert") -> 7 | F18: =IFERROR(AVERAGEIFS(Merged_Data!J:J,Merged_Data!C:C,A18,Merged_Data!J:J,"<>0"),"No Data") -> 509601.76 | G18: =RANK(B18,B$2:B$51,0) -> 35
A19: =State_Ref!B34 -> NC | B19: =COUNTIFS(Merged_Data!C:C,A19) -> 120 | C19: =IFERROR(AVERAGEIFS(Merged_Data!H:H,Merged_Data!C:C,A19,Merged_Data!H:H,"<>0"),"No Data") -> 3.3 | D19: =COUNTIFS(Merged_Data!C:C,A19,Merged_Data!G:G,"Yes") -> 105 | E19: =COUNTIFS(Merged_Data!C:C,A19,Merged_Data!K:K,"Hospital Desert") -> 31 | F19: =IFERROR(AVERAGEIFS(Merged_Data!J:J,Merged_Data!C:C,A19,Merged_Data!J:J,"<>0"),"No Data") -> 272209.26 | G19: =RANK(B19,B$2:B$51,0) -> 18
A20: =State_Ref!B37 -> OK | B20: =COUNTIFS(Merged_Data!C:C,A20) -> 135 | C20: =IFERROR(AVERAGEIFS(Merged_Data!H:H,Merged_Data!C:C,A20,Merged_Data!H:H,"<>0"),"No Data") -> 3.2903226 | D20: =COUNTIFS(Merged_Data!C:C,A20,Merged_Data!G:G,"Yes") -> 120 | E20: =COUNTIFS(Merged_Data!C:C,A20,Merged_Data!K:K,"Hospital Desert") -> 8 | F20: =IFERROR(AVERAGEIFS(Merged_Data!J:J,Merged_Data!C:C,A20,Merged_Data!J:J,"<>0"),"No Data") -> 258583.41 | G20: =RANK(B20,B$2:B$51,0) -> 15
A21: =State_Ref!B27 -> MT | B21: =COUNTIFS(Merged_Data!C:C,A21) -> 63 | C21: =IFERROR(AVERAGEIFS(Merged_Data!H:H,Merged_Data!C:C,A21,Merged_Data!H:H,"<>0"),"No Data") -> 3.25 | D21: =COUNTIFS(Merged_Data!C:C,A21,Merged_Data!G:G,"Yes") -> 60 | E21: =COUNTIFS(Merged_Data!C:C,A21,Merged_Data!K:K,"Hospital Desert") -> 0 | F21: =IFERROR(AVERAGEIFS(Merged_Data!J:J,Merged_Data!C:C,A21,Merged_Data!J:J,"<>0"),"No Data") -> 31689.905 | G21: =RANK(B21,B$2:B$51,0) -> 32
A22: =State_Ref!B35 -> ND | B22: =COUNTIFS(Merged_Data!C:C,A22) -> 47 | C22: =IFERROR(AVERAGEIFS(Merged_Data!H:H,Merged_Data!C:C,A22,Merged_Data!H:H,"<>0"),"No Data") -> 3.25 | D22: =COUNTIFS(Merged_Data!C:C,A22,Merged_Data!G:G,"Yes") -> 45 | E22: =COUNTIFS(Merged_Data!C:C,A22,Merged_Data!K:K,"Hospital Desert") -> 0 | F22: =IFERROR(AVERAGEIFS(Merged_Data!J:J,Merged_Data!C:C,A22,Merged_Data!J:J,"<>0"),"No Data") -> 35313.298 | G22: =RANK(B22,B$2:B$51,0) -> 39
A23: =State_Ref!B38 -> OR | B23: =COUNTIFS(Merged_Data!C:C,A23) -> 62 | C23: =IFERROR(AVERAGEIFS(Merged_Data!H:H,Merged_Data!C:C,A23,Merged_Data!H:H,"<>0"),"No Data") -> 3.25 | D23: =COUNTIFS(Merged_Data!C:C,A23,Merged_Data!G:G,"Yes") -> 58 | E23: =COUNTIFS(Merged_Data!C:C,A23,Merged_Data!K:K,"Hospital Desert") -> 5 | F23: =IFERROR(AVERAGEIFS(Merged_Data!J:J,Merged_Data!C:C,A23,Merged_Data!J:J,"<>0"),"No Data") -> 266197.37 | G23: =RANK(B23,B$2:B$51,0) -> 33
A24: =State_Ref!B46 -> VT | B24: =COUNTIFS(Merged_Data!C:C,A24) -> 17 | C24: =IFERROR(AVERAGEIFS(Merged_Data!H:H,Merged_Data!C:C,A24,Merged_Data!H:H,"<>0"),"No Data") -> 3.25 | D24: =COUNTIFS(Merged_Data!C:C,A24,Merged_Data!G:G,"Yes") -> 15 | E24: =COUNTIFS(Merged_Data!C:C,A24,Merged_Data!K:K,"Hospital Desert") -> 3 | F24: =IFERROR(AVERAGEIFS(Merged_Data!J:J,Merged_Data!C:C,A24,Merged_Data!J:J,"<>0"),"No Data") -> 52693.235 | G24: =RANK(B24,B$2:B$51,0) -> 48
A25: =State_Ref!B16 -> IA | B25: =COUNTIFS(Merged_Data!C:C,A25) -> 118 | C25: =IFERROR(AVERAGEIFS(Merged_Data!H:H,Merged_Data!C:C,A25,Merged_Data!H:H,"<>0"),"No Data") -> 3.2419355 | D25: =COUNTIFS(Merged_Data!C:C,A25,Merged_Data!G:G,"Yes") -> 113 | E25: =COUNTIFS(Merged_Data!C:C,A25,Merged_Data!K:K,"Hospital Desert") -> 2 | F25: =IFERROR(AVERAGEIFS(Merged_Data!J:J,Merged_Data!C:C,A25,Merged_Data!J:J,"<>0"),"No Data") -> 60685.376 | G25: =RANK(B25,B$2:B$51,0) -> 19
A26: =State_Ref!B48 -> WA | B26: =COUNTIFS(Merged_Data!C:C,A26) -> 100 | C26: =IFERROR(AVERAGEIFS(Merged_Data!H:H,Merged_Data!C:C,A26,Merged_Data!H:H,"<>0"),"No Data") -> 3.2333333 | D26: =COUNTIFS(Merged_Data!C:C,A26,Merged_Data!G:G,"Yes") -> 90 | E26: =COUNTIFS(Merged_Data!C:C,A26,Merged_Data!K:K,"Hospital Desert") -> 7 | F26: =IFERROR(AVERAGEIFS(Merged_Data!J:J,Merged_Data!C:C,A26,Merged_Data!J:J,"<>0"),"No Data") -> 706244.09 | G26: =RANK(B26,B$2:B$51,0) -> 23
A27: =State_Ref!B20 -> ME | B27: =COUNTIFS(Merged_Data!C:C,A27) -> 36 | C27: =IFERROR(AVERAGEIFS(Merged_Data!H:H,Merged_Data!C:C,A27,Merged_Data!H:H,"<>0"),"No Data") -> 3.2083333 | D27: =COUNTIFS(Merged_Data!C:C,A27,Merged_Data!G:G,"Yes") -> 32 | E27: =COUNTIFS(Merged_Data!C:C,A27,Merged_Data!K:K,"Hospital Desert") -> 1 | F27: =IFERROR(AVERAGEIFS(Merged_Data!J:J,Merged_Data!C:C,A27,Merged_Data!J:J,"<>0"),"No Data") -> 119031.03 | G27: =RANK(B27,B$2:B$51,0) -> 42
A28: =State_Ref!B22 -> MA | B28: =COUNTIFS(Merged_Data!C:C,A28) -> 84 | C28: =IFERROR(AVERAGEIFS(Merged_Data!H:H,Merged_Data!C:C,A28,Merged_Data!H:H,"<>0"),"No Data") -> 3.2037037 | D28: =COUNTIFS(Merged_Data!C:C,A28,Merged_Data!G:G,"Yes") -> 60 | E28: =COUNTIFS(Merged_Data!C:C,A28,Merged_Data!K:K,"Hospital Desert") -> 1 | F28: =IFERROR(AVERAGEIFS(Merged_Data!J:J,Merged_Data!C:C,A28,Merged_Data!J:J,"<>0"),"No Data") -> 809645.4 | G28: =RANK(B28,B$2:B$51,0) -> 29
A29: =State_Ref!B12 -> HI | B29: =COUNTIFS(Merged_Data!C:C,A29) -> 24 | C29: =IFERROR(AVERAGEIFS(Merged_Data!H:H,Merged_Data!C:C,A29,Merged_Data!H:H,"<>0"),"No Data") -> 3.1818182 | D29: =COUNTIFS(Merged_Data!C:C,A29,Merged_Data!G:G,"Yes") -> 21 | E29: =COUNTIFS(Merged_Data!C:C,A29,Merged_Data!K:K,"Hospital Desert") -> 0 | F29: =IFERROR(AVERAGEIFS(Merged_Data!J:J,Merged_Data!C:C,A29,Merged_Data!J:J,"<>0"),"No Data") -> 541606.62 | G29: =RANK(B29,B$2:B$51,0) -> 47
A30: =State_Ref!B17 -> KS | B30: =COUNTIFS(Merged_Data!C:C,A30) -> 138 | C30: =IFERROR(AVERAGEIFS(Merged_Data!H:H,Merged_Data!C:C,A30,Merged_Data!H:H,"<>0"),"No Data") -> 3.1818182 | D30: =COUNTIFS(Merged_Data!C:C,A30,Merged_Data!G:G,"Yes") -> 117 | E30: =COUNTIFS(Merged_Data!C:C,A30,Merged_Data!K:K,"Hospital Desert") -> 2 | F30: =IFERROR(AVERAGEIFS(Merged_Data!J:J,Merged_Data!C:C,A30,Merged_Data!J:J,"<>0"),"No Data") -> 110588.15 | G30: =RANK(B30,B$2:B$51,0) -> 13
A31: =State_Ref!B30 -> NH | B31: =COUNTIFS(Merged_Data!C:C,A31) -> 28 | C31: =IFERROR(AVERAGEIFS(Merged_Data!H:H,Merged_Data!C:C,A31,Merged_Data!H:H,"<>0"),"No Data") -> 3.173913 | D31: =COUNTIFS(Merged_Data!C:C,A31,Merged_Data!G:G,"Yes") -> 26 | E31: =COUNTIFS(Merged_Data!C:C,A31,Merged_Data!K:K,"Hospital Desert") -> 2 | F31: =IFERROR(AVERAGEIFS(Merged_Data!J:J,Merged_Data!C:C,A31,Merged_Data!J:J,"<>0"),"No Data") -> 186388.57 | G31: =RANK(B31,B$2:B$51,0) -> 45
A32: =State_Ref!B31 -> NJ | B32: =COUNTIFS(Merged_Data!C:C,A32) -> 79 | C32: =IFERROR(AVERAGEIFS(Merged_Data!H:H,Merged_Data!C:C,A32,Merged_Data!H:H,"<>0"),"No Data") -> 3.147541 | D32: =COUNTIFS(Merged_Data!C:C,A32,Merged_Data!G:G,"Yes") -> 57 | E32: =COUNTIFS(Merged_Data!C:C,A32,Merged_Data!K:K,"Hospital Desert") -> 5 | F32: =IFERROR(AVERAGEIFS(Merged_Data!J:J,Merged_Data!C:C,A32,Merged_Data!J:J,"<>0"),"No Data") -> 626092.61 | G32: =RANK(B32,B$2:B$51,0) -> 30
A33: =State_Ref!B9 -> DE | B33: =COUNTIFS(Merged_Data!C:C,A33) -> 13 | C33: =IFERROR(AVERAGEIFS(Merged_Data!H:H,Merged_Data!C:C,A33,Merged_Data!H:H,"<>0"),"No Data") -> 3.1428571 | D33: =COUNTIFS(Merged_Data!C:C,A33,Merged_Data!G:G,"Yes") -> 9 | E33: =COUNTIFS(Merged_Data!C:C,A33,Merged_Data!K:K,"Hospital Desert") -> 0 | F33: =IFERROR(AVERAGEIFS(Merged_Data!J:J,Merged_Data!C:C,A33,Merged_Data!J:J,"<>0"),"No Data") -> 431870.31 | G33: =RANK(B33,B$2:B$51,0) -> 49
A34: =State_Ref!B26 -> MO | B34: =COUNTIFS(Merged_Data!C:C,A34) -> 121 | C34: =IFERROR(AVERAGEIFS(Merged_Data!H:H,Merged_Data!C:C,A34,Merged_Data!H:H,"<>0"),"No Data") -> 3.1375 | D34: =COUNTIFS(Merged_Data!C:C,A34,Merged_Data!G:G,"Yes") -> 106 | E34: =COUNTIFS(Merged_Data!C:C,A34,Merged_Data!K:K,"Hospital Desert") -> 9 | F34: =IFERROR(AVERAGEIFS(Merged_Data!J:J,Merged_Data!C:C,A34,Merged_Data!J:J,"<>0"),"No Data") -> 159513.78 | G34: =RANK(B34,B$2:B$51,0) -> 17
A35: =State_Ref!B4 -> AZ | B35: =COUNTIFS(Merged_Data!C:C,A35) -> 107 | C35: =IFERROR(AVERAGEIFS(Merged_Data!H:H,Merged_Data!C:C,A35,Merged_Data!H:H,"<>0"),"No Data") -> 3.1090909 | D35: =COUNTIFS(Merged_Data!C:C,A35,Merged_Data!G:G,"Yes") -> 74 | E35: =COUNTIFS(Merged_Data!C:C,A35,Merged_Data!K:K,"Hospital Desert") -> 1 | F35: =IFERROR(AVERAGEIFS(Merged_Data!J:J,Merged_Data!C:C,A35,Merged_Data!J:J,"<>0"),"No Data") -> 2572055.5 | G35: =RANK(B35,B$2:B$51,0) -> 21
A36: =State_Ref!B6 -> CA | B36: =COUNTIFS(Merged_Data!C:C,A36) -> 378 | C36: =IFERROR(AVERAGEIFS(Merged_Data!H:H,Merged_Data!C:C,A36,Merged_Data!H:H,"<>0"),"No Data") -> 3.1 | D36: =COUNTIFS(Merged_Data!C:C,A36,Merged_Data!G:G,"Yes") -> 285 | E36: =COUNTIFS(Merged_Data!C:C,A36,Merged_Data!K:K,"Hospital Desert") -> 5 | F36: =IFERROR(AVERAGEIFS(Merged_Data!J:J,Merged_Data!C:C,A36,Merged_Data!J:J,"<>0"),"No Data") -> 3314074.9 | G36: =RANK(B36,B$2:B$51,0) -> 2
A37: =State_Ref!B23 -> MI | B37: =COUNTIFS(Merged_Data!C:C,A37) -> 148 | C37: =IFERROR(AVERAGEIFS(Merged_Data!H:H,Merged_Data!C:C,A37,Merged_Data!H:H,"<>0"),"No Data") -> 3.0851064 | D37: =COUNTIFS(Merged_Data!C:C,A37,Merged_Data!G:G,"Yes") -> 119 | E37: =COUNTIFS(Merged_Data!C:C,A37,Merged_Data!K:K,"Hospital Desert") -> 15 | F37: =IFERROR(AVERAGEIFS(Merged_Data!J:J,Merged_Data!C:C,A37,Merged_Data!J:J,"<>0"),"No Data") -> 515484.56 | G37: =RANK(B37,B$2:B$51,0) -> 11
A38: =State_Ref!B43 -> TN | B38: =COUNTIFS(Merged_Data!C:C,A38) -> 122 | C38: =IFERROR(AVERAGEIFS(Merged_Data!H:H,Merged_Data!C:C,A38,Merged_Data!H:H,"<>0"),"No Data") -> 3.0833333 | D38: =COUNTIFS(Merged_Data!C:C,A38,Merged_Data!G:G,"Yes") -> 98 | E38: =COUNTIFS(Merged_Data!C:C,A38,Merged_Data!K:K,"Hospital Desert") -> 20 | F38: =IFERROR(AVERAGEIFS(Merged_Data!J:J,Merged_Data!C:C,A38,Merged_Data!J:J,"<>0"),"No Data") -> 276340.95 | G38: =RANK(B38,B$2:B$51,0) -> 16
A39: =State_Ref!B10 -> FL | B39: =COUNTIFS(Merged_Data!C:C,A39) -> 221 | C39: =IFERROR(AVERAGEIFS(Merged_Data!H:H,Merged_Data!C:C,A39,Merged_Data!H:H,"<>0"),"No Data") -> 3.0650888 | D39: =COUNTIFS(Merged_Data!C:C,A39,Merged_Data!G:G,"Yes") -> 184 | E39: =COUNTIFS(Merged_Data!C:C,A39,Merged_Data!K:K,"Hospital Desert") -> 3 | F39: =IFERROR(AVERAGEIFS(Merged_Data!J:J,Merged_Data!C:C,A39,Merged_Data!J:J,"<>0"),"No Data") -> 991661.16 | G39: =RANK(B39,B$2:B$51,0) -> 3
A40: =State_Ref!B14 -> IL | B40: =COUNTIFS(Merged_Data!C:C,A40) -> 194 | C40: =IFERROR(AVERAGEIFS(Merged_Data!H:H,Merged_Data!C:C,A40,Merged_Data!H:H,"<>0"),"No Data") -> 3.0294118 | D40: =COUNTIFS(Merged_Data!C:C,A40,Merged_Data!G:G,"Yes") -> 175 | E40: =COUNTIFS(Merged_Data!C:C,A40,Merged_Data!K:K,"Hospital Desert") -> 4 | F40: =IFERROR(AVERAGEIFS(Merged_Data!J:J,Merged_Data!C:C,A40,Merged_Data!J:J,"<>0"),"No Data") -> 1817508.8 | G40: =RANK(B40,B$2:B$51,0) -> 5
A41: =State_Ref!B29 -> NV | B41: =COUNTIFS(Merged_Data!C:C,A41) -> 46 | C41: =IFERROR(AVERAGEIFS(Merged_Data!H:H,Merged_Data!C:C,A41,Merged_Data!H:H,"<>0"),"No Data") -> 3 | D41: =COUNTIFS(Merged_Data!C:C,A41,Merged_Data!G:G,"Yes") -> 37 | E41: =COUNTIFS(Merged_Data!C:C,A41,Merged_Data!K:K,"Hospital Desert") -> 5 | F41: =IFERROR(AVERAGEIFS(Merged_Data!J:J,Merged_Data!C:C,A41,Merged_Data!J:J,"<>0"),"No Data") -> 1456993.1 | G41: =RANK(B41,B$2:B$51,0) -> 40
A42: =State_Ref!B11 -> GA | B42: =COUNTIFS(Merged_Data!C:C,A42) -> 149 | C42: =IFERROR(AVERAGEIFS(Merged_Data!H:H,Merged_Data!C:C,A42,Merged_Data!H:H,"<>0"),"No Data") -> 2.9404762 | D42: =COUNTIFS(Merged_Data!C:C,A42,Merged_Data!G:G,"Yes") -> 103 | E42: =COUNTIFS(Merged_Data!C:C,A42,Merged_Data!K:K,"Hospital Desert") -> 22 | F42: =IFERROR(AVERAGEIFS(Merged_Data!J:J,Merged_Data!C:C,A42,Merged_Data!J:J,"<>0"),"No Data") -> 193619.97 | G42: =RANK(B42,B$2:B$51,0) -> 10
A43: =State_Ref!B3 -> AK | B43: =COUNTIFS(Merged_Data!C:C,A43) -> 25 | C43: =IFERROR(AVERAGEIFS(Merged_Data!H:H,Merged_Data!C:C,A43,Merged_Data!H:H,"<>0"),"No Data") -> 2.9 | D43: =COUNTIFS(Merged_Data!C:C,A43,Merged_Data!G:G,"Yes") -> 24 | E43: =COUNTIFS(Merged_Data!C:C,A43,Merged_Data!K:K,"Hospital Desert") -> 9 | F43: =IFERROR(AVERAGEIFS(Merged_Data!J:J,Merged_Data!C:C,A43,Merged_Data!J:J,"<>0"),"No Data") -> 5929.3333 | G43: =RANK(B43,B$2:B$51,0) -> 46
A44: =State_Ref!B5 -> AR | B44: =COUNTIFS(Merged_Data!C:C,A44) -> 91 | C44: =IFERROR(AVERAGEIFS(Merged_Data!H:H,Merged_Data!C:C,A44,Merged_Data!H:H,"<>0"),"No Data") -> 2.8409091 | D44: =COUNTIFS(Merged_Data!C:C,A44,Merged_Data!G:G,"Yes") -> 82 | E44: =COUNTIFS(Merged_Data!C:C,A44,Merged_Data!K:K,"Hospital Desert") -> 5 | F44: =IFERROR(AVERAGEIFS(Merged_Data!J:J,Merged_Data!C:C,A44,Merged_Data!J:J,"<>0"),"No Data") -> 122532.4 | G44: =RANK(B44,B$2:B$51,0) -> 28
A45: =State_Ref!B19 -> LA | B45: =COUNTIFS(Merged_Data!C:C,A45) -> 161 | C45: =IFERROR(AVERAGEIFS(Merged_Data!H:H,Merged_Data!C:C,A45,Merged_Data!H:H,"<>0"),"No Data") -> 2.8135593 | D45: =COUNTIFS(Merged_Data!C:C,A45,Merged_Data!G:G,"Yes") -> 98 | E45: =COUNTIFS(Merged_Data!C:C,A45,Merged_Data!K:K,"Hospital Desert") -> 23 | F45: =IFERROR(AVERAGEIFS(Merged_Data!J:J,Merged_Data!C:C,A45,Merged_Data!J:J,"<>0"),"No Data") -> No Data | G45: =RANK(B45,B$2:B$51,0) -> 8
A46: =State_Ref!B33 -> NY | B46: =COUNTIFS(Merged_Data!C:C,A46) -> 191 | C46: =IFERROR(AVERAGEIFS(Merged_Data!H:H,Merged_Data!C:C,A46,Merged_Data!H:H,"<>0"),"No Data") -> 2.7720588 | D46: =COUNTIFS(Merged_Data!C:C,A46,Merged_Data!G:G,"Yes") -> 158 | E46: =COUNTIFS(Merged_Data!C:C,A46,Merged_Data!K:K,"Hospital Desert") -> 15 | F46: =IFERROR(AVERAGEIFS(Merged_Data!J:J,Merged_Data!C:C,A46,Merged_Data!J:J,"<>0"),"No Data") -> 874307.34 | G46: =RANK(B46,B$2:B$51,0) -> 6
A47: =State_Ref!B49 -> WV | B47: =COUNTIFS(Merged_Data!C:C,A47) -> 55 | C47: =IFERROR(AVERAGEIFS(Merged_Data!H:H,Merged_Data!C:C,A47,Merged_Data!H:H,"<>0"),"No Data") -> 2.7647059 | D47: =COUNTIFS(Merged_Data!C:C,A47,Merged_Data!G:G,"Yes") -> 49 | E47: =COUNTIFS(Merged_Data!C:C,A47,Merged_Data!K:K,"Hospital Desert") -> 5 | F47: =IFERROR(AVERAGEIFS(Merged_Data!J:J,Merged_Data!C:C,A47,Merged_Data!J:J,"<>0"),"No Data") -> 53987.37 | G47: =RANK(B47,B$2:B$51,0) -> 36
A48: =State_Ref!B18 -> KY | B48: =COUNTIFS(Merged_Data!C:C,A48) -> 103 | C48: =IFERROR(AVERAGEIFS(Merged_Data!H:H,Merged_Data!C:C,A48,Merged_Data!H:H,"<>0"),"No Data") -> 2.761194 | D48: =COUNTIFS(Merged_Data!C:C,A48,Merged_Data!G:G,"Yes") -> 94 | E48: =COUNTIFS(Merged_Data!C:C,A48,Merged_Data!K:K,"Hospital Desert") -> 9 | F48: =IFERROR(AVERAGEIFS(Merged_Data!J:J,Merged_Data!C:C,A48,Merged_Data!J:J,"<>0"),"No Data") -> 123528.2 | G48: =RANK(B48,B$2:B$51,0) -> 22
A49: =State_Ref!B2 -> AL | B49: =COUNTIFS(Merged_Data!C:C,A49) -> 100 | C49: =IFERROR(AVERAGEIFS(Merged_Data!H:H,Merged_Data!C:C,A49,Merged_Data!H:H,"<>0"),"No Data") -> 2.7118644 | D49: =COUNTIFS(Merged_Data!C:C,A49,Merged_Data!G:G,"Yes") -> 91 | E49: =COUNTIFS(Merged_Data!C:C,A49,Merged_Data!K:K,"Hospital Desert") -> 15 | F49: =IFERROR(AVERAGEIFS(Merged_Data!J:J,Merged_Data!C:C,A49,Merged_Data!J:J,"<>0"),"No Data") -> 179027.23 | G49: =RANK(B49,B$2:B$51,0) -> 23
A50: =State_Ref!B32 -> NM | B50: =COUNTIFS(Merged_Data!C:C,A50) -> 45 | C50: =IFERROR(AVERAGEIFS(Merged_Data!H:H,Merged_Data!C:C,A50,Merged_Data!H:H,"<>0"),"No Data") -> 2.4782609 | D50: =COUNTIFS(Merged_Data!C:C,A50,Merged_Data!G:G,"Yes") -> 38 | E50: =COUNTIFS(Merged_Data!C:C,A50,Merged_Data!K:K,"Hospital Desert") -> 1 | F50: =IFERROR(AVERAGEIFS(Merged_Data!J:J,Merged_Data!C:C,A50,Merged_Data!J:J,"<>0"),"No Data") -> 178424.95 | G50: =RANK(B50,B$2:B$51,0) -> 41
A51: =State_Ref!B25 -> MS | B51: =COUNTIFS(Merged_Data!C:C,A51) -> 108 | C51: =IFERROR(AVERAGEIFS(Merged_Data!H:H,Merged_Data!C:C,A51,Merged_Data!H:H,"<>0"),"No Data") -> 2.3269231 | D51: =COUNTIFS(Merged_Data!C:C,A51,Merged_Data!G:G,"Yes") -> 91 | E51: =COUNTIFS(Merged_Data!C:C,A51,Merged_Data!K:K,"Hospital Desert") -> 7 | F51: =IFERROR(AVERAGEIFS(Merged_Data!J:J,Merged_Data!C:C,A51,Merged_Data!J:J,"<>0"),"No Data") -> 64768.286 | G51: =RANK(B51,B$2:B$51,0) -> 20

Sheet Pivot_Tables
A1: State | B1: Hospitals by State-Count of Facility Name | E1: Hospital Ownership Breakdown | F1: Count of Facility Name | H1: Hospital Deserts by State | I1: Hospital Desert | K1: {=Analysis!A1:C11} -> State | L1: Total_Hospitals | M1: Avg_Rating
A2: CA | B2: 378 | E2: Department of Defense | F2: 32 | K2: UT | L2: 52 | M2: 4.2413793
A3: FL | B3: 221 | E3: Government - Federal | F3: 43 | H3: State | I3: Count of Facility Name | K3: CO | L3: 97 | M3: 3.9591837
A4: GA | B4: 149 | E4: Government - Hospital District or Authority | F4: 516 | H4: AL | I4: 15 | K4: SD | L4: 61 | M4: 3.8888889
A5: IL | B5: 194 | E5: Government - Local | F5: 397 | H5: GA | I5: 22 | K5: WI | L5: 141 | M5: 3.7790698
A6: IN | B6: 151 | E6: Government - State | F6: 209 | H6: LA | I6: 23 | K6: MN | L6: 136 | M6: 3.7719298
A7: LA | B7: 161 | E7: Physician | F7: 81 | H7: MI | I7: 15 | K7: VA | L7: 96 | M7: 3.6842105
A8: NY | B8: 191 | E8: Proprietary | F8: 1067 | H8: NC | I8: 31 | K8: OH | L8: 196 | M8: 3.578125
A9: OH | B9: 196 | E9: Tribal | F9: 16 | H9: NY | I9: 15 | K9: ID | L9: 48 | M9: 3.5454545
A10: PA | B10: 187 | E10: Veterans Health Administration | F10: 132 | H10: OH | I10: 17 | K10: RI | L10: 13 | M10: 3.5454545
A11: TX | B11: 468 | E11: Voluntary non-profit - Church | F11: 268 | H11: TN | I11: 20 | K11: NE | L11: 93 | M11: 3.5
A12: Grand Total | B12: 2296 | E12: Voluntary non-profit - Other | F12: 355 | H12: TX | I12: 24
E13: Voluntary non-profit - Private | F13: 2316 | H13: VA | I13: 19
E14: Grand Total | F14: 5432 | H14: Grand Total | I14: 201

Sheet Dashboard
A1: American Hospital Access Dashboard
A4: CMS Hospital General Information · U.S. Census Bureau 2025 · 5,432 facilities
B7: TOTAL HOSPITALS | N7: AVG STAR RATING | Z7: WITH EMERGENCY | AL7: HOSPITAL DESERTS
B9: =COUNTA(Raw_Hospitals!A:A)-1 -> 5432 | N9: =ROUND(AVERAGE(Analysis!C2:C51),1)&" ★" -> 3.2 ★ | Z9: =TEXT(COUNTIF(Raw_Hospitals!G:G,"Yes")/(COUNTA(Raw_Hospitals!A:A)-1),"0%") -> 83% | AL9: =COUNTIF(Merged_Data!K:K,"Hospital Desert") -> 373
